stylist/__init__.py
stylist/__main__.py
stylist/configuration.py
stylist/engine.py
stylist/fortran.py
stylist/issue.py
stylist/rule.py
stylist/source.py
stylist/style.py
stylist-0.4.1.dist-info/LICENSE
stylist-0.4.1.dist-info/METADATA
stylist-0.4.1.dist-info/WHEEL
stylist-0.4.1.dist-info/entry_points.txt
stylist-0.4.1.dist-info/top_level.txt
stylist-0.4.1.dist-info/RECORD
