Metadata-Version: 2.1
Name: stylist
Version: 0.4.1
Summary: Flexible source code style checking tool
Home-page: https://github.com/MetOffice/stylist
Author: Met Office
License: BSD 3-Clause License
Project-URL: homepage, https://github.com/MetOffice/stylist/
Project-URL: documentation, https://metoffice.github.io/stylist
Project-URL: Bug Reports, https://github.com/MetOffice/stylist/issues
Project-URL: repository, https://github.com/MetOffice/stylist/
Keywords: linter fortran psyclone
Classifier: Programming Language :: Python :: 3
Requires-Python: <4,>=3.7
License-File: LICENSE
Requires-Dist: fparser >=0.1.2
Provides-Extra: dev
Requires-Dist: check-manifest ; extra == 'dev'
Requires-Dist: flake8 ; extra == 'dev'
Provides-Extra: docs
Requires-Dist: sphinx <7.0.0 ; extra == 'docs'
Requires-Dist: sphinx-autodoc-typehints ; extra == 'docs'
Requires-Dist: sphinx-rtd-theme >=1.2.2 ; extra == 'docs'
Provides-Extra: performance
Requires-Dist: pytest ; extra == 'performance'
Requires-Dist: pytest-benchmark ; extra == 'performance'
Requires-Dist: matplotlib ; extra == 'performance'
Provides-Extra: release
Requires-Dist: setuptools ; extra == 'release'
Requires-Dist: wheel ; extra == 'release'
Requires-Dist: twine ; extra == 'release'
Provides-Extra: test
Requires-Dist: pytest ; extra == 'test'
Requires-Dist: pytest-cov ; extra == 'test'
Requires-Dist: mypy ; extra == 'test'
